{
  "beforeCount": 1,
  "deletedCount": 1,
  "deleted": [
    {
      "id": "e4d42998-a12a-4cd4-a6eb-d23e761406d5",
      "title": "【運営確認用】ぶらんかーず参加管理デモ",
      "status": "accepting"
    }
  ],
  "created": [
    {
      "id": "2b60aeb6-0bbf-4aa8-90d4-64c51ba38c20",
      "title": "【運営確認用】受付中・参加申請デモ",
      "status": "accepting",
      "max_participants": 35,
      "threshold": 30
    },
    {
      "id": "eb68f7e5-bfb7-491c-8429-3ad790a5c31d",
      "title": "【運営確認用】満員締切デモ",
      "status": "closed",
      "max_participants": 3,
      "threshold": 3
    },
    {
      "id": "25f98b4c-3304-49ef-824c-4dd91d6e1472",
      "title": "【運営確認用】締切日時超過デモ",
      "status": "closed",
      "max_participants": 35,
      "threshold": 30
    },
    {
      "id": "f14e3bf0-85d4-48bf-8427-0d90f0d553ab",
      "title": "【運営確認用】下書きデモ",
      "status": "draft",
      "max_participants": 35,
      "threshold": 30
    }
  ],
  "visibleToUsersCount": 3,
  "finalEventCount": 4,
  "finalEvents": [
    {
      "id": "f14e3bf0-85d4-48bf-8427-0d90f0d553ab",
      "title": "【運営確認用】下書きデモ",
      "status": "draft",
      "event_date": "2026-06-27T10:00:00+00:00",
      "event_end_date": "2026-06-27T12:00:00+00:00",
      "max_participants": 35,
      "threshold": 30
    },
    {
      "id": "25f98b4c-3304-49ef-824c-4dd91d6e1472",
      "title": "【運営確認用】締切日時超過デモ",
      "status": "closed",
      "event_date": "2026-06-20T10:00:00+00:00",
      "event_end_date": "2026-06-20T12:00:00+00:00",
      "max_participants": 35,
      "threshold": 30
    },
    {
      "id": "eb68f7e5-bfb7-491c-8429-3ad790a5c31d",
      "title": "【運営確認用】満員締切デモ",
      "status": "closed",
      "event_date": "2026-06-13T10:00:00+00:00",
      "event_end_date": "2026-06-13T12:00:00+00:00",
      "max_participants": 3,
      "threshold": 3
    },
    {
      "id": "2b60aeb6-0bbf-4aa8-90d4-64c51ba38c20",
      "title": "【運営確認用】受付中・参加申請デモ",
      "status": "accepting",
      "event_date": "2026-06-06T10:00:00+00:00",
      "event_end_date": "2026-06-06T12:00:00+00:00",
      "max_participants": 35,
      "threshold": 30
    }
  ],
  "participants": [
    {
      "event_id": "25f98b4c-3304-49ef-824c-4dd91d6e1472",
      "name": "小林 亮",
      "status": "active",
      "slot_number": 1,
      "is_guest": false
    },
    {
      "event_id": "25f98b4c-3304-49ef-824c-4dd91d6e1472",
      "name": "加藤 真由",
      "status": "active",
      "slot_number": 2,
      "is_guest": false
    },
    {
      "event_id": "2b60aeb6-0bbf-4aa8-90d4-64c51ba38c20",
      "name": "佐藤 太郎(たろちゃん)",
      "status": "active",
      "slot_number": 1,
      "is_guest": false
    },
    {
      "event_id": "2b60aeb6-0bbf-4aa8-90d4-64c51ba38c20",
      "name": "鈴木 花子",
      "status": "active",
      "slot_number": 2,
      "is_guest": false
    },
    {
      "event_id": "2b60aeb6-0bbf-4aa8-90d4-64c51ba38c20",
      "name": "山田 一郎",
      "status": "active",
      "slot_number": 3,
      "is_guest": false
    },
    {
      "event_id": "2b60aeb6-0bbf-4aa8-90d4-64c51ba38c20",
      "name": "田中 友人(佐藤の友達)",
      "status": "active",
      "slot_number": 4,
      "is_guest": true
    },
    {
      "event_id": "eb68f7e5-bfb7-491c-8429-3ad790a5c31d",
      "name": "高橋 健太",
      "status": "active",
      "slot_number": 1,
      "is_guest": false
    },
    {
      "event_id": "eb68f7e5-bfb7-491c-8429-3ad790a5c31d",
      "name": "伊藤 美咲",
      "status": "active",
      "slot_number": 2,
      "is_guest": false
    },
    {
      "event_id": "eb68f7e5-bfb7-491c-8429-3ad790a5c31d",
      "name": "渡辺 大輔",
      "status": "active",
      "slot_number": 3,
      "is_guest": false
    }
  ]
}